LICENSE
README.md
setup.py
lib/mmio.c
rvtrace/__init__.py
rvtrace/__main__.py
rvtrace/cli.py
rvtrace/device.py
rvtrace/encoder.py
rvtrace/funnel.py
rvtrace/helper.py
rvtrace/iommap.py
rvtrace/timestamp.py
rvtrace/topology.py
rvtrace.egg-info/PKG-INFO
rvtrace.egg-info/SOURCES.txt
rvtrace.egg-info/dependency_links.txt
rvtrace.egg-info/entry_points.txt
rvtrace.egg-info/top_level.txt
rvtrace/platforms/__init__.py
rvtrace/platforms/p550.cfg
rvtrace/platforms/p550.md